[
  {
    "name": "电脑/办公",
    "subs": [
      "键鼠套装",
      "键盘",
      "鼠标",
      "手写板",
      "电脑配件",
      "电脑包"
    ]
  },
  {
    "name": "手机",
    "subs": [
      "手机1",
      "手机2",
      "手机3",
      "手机4"
    ]
  },
  {
    "name": "母婴",
    "subs": [
      "母婴1",
      "母婴2",
      "母婴3",
      "母婴4"
    ]
  },
  {
    "name": "家电",
    "subs": [
      "家电1",
      "家电2",
      "家电3",
      "家电4"
    ]
  },
  {
    "name": "汽车用品",
    "subs": [
      "汽车用品1",
      "汽车用品2",
      "汽车用品3",
      "汽车用品4"
    ]
  },
  {
    "name": "厨卫电器",
    "subs": [
      "厨卫电器1",
      "厨卫电器2",
      "厨卫电器3",
      "厨卫电器4"
    ]
  }
]